mcp_allthetools/__init__.py
mcp_allthetools/server.py
mcp_allthetools/tools.py
mcp_allthetools-0.1.0.dist-info/METADATA
mcp_allthetools-0.1.0.dist-info/WHEEL
mcp_allthetools-0.1.0.dist-info/entry_points.txt
mcp_allthetools-0.1.0.dist-info/licenses/LICENSE
mcp_allthetools-0.1.0.dist-info/RECORD
